resif/__init__.py
resif/resif.py
resif/configManager.py
resif/buildSwSets.py
resif/bootstrapEB.py
resif-2.0.2.dist-info/WHEEL
resif-2.0.2.dist-info/entry_points.txt
resif-2.0.2.dist-info/metadata.json
resif-2.0.2.dist-info/top_level.txt
resif-2.0.2.dist-info/METADATA
resif-2.0.2.dist-info/DESCRIPTION.rst
resif-2.0.2.dist-info/RECORD
