Metadata-Version: 2.0
Name: resif
Version: 2.0.2
Summary: Command line interface to deploy an EasyBuild infrastructure and manage it.
Home-page: https://hpc.uni.lu/
Author: ULHPC
Author-email: hpc-sysadmins@uni.lu
License: GPLv2
Platform: UNKNOWN
Classifier: License :: OSI Approved
Classifier: License :: OSI Approved :: GNU General Public License v2 (GPLv2)
Classifier: Programming Language :: Python
Classifier: Programming Language :: Python :: 2
Classifier: Programming Language :: Python :: 2.6
Classifier: Programming Language :: Python :: 2.7
Classifier: Operating System :: Unix
Classifier: Operating System :: MacOS
Classifier: Operating System :: POSIX
Classifier: Operating System :: POSIX :: Linux
Classifier: Topic :: Scientific/Engineering
Classifier: Topic :: System :: Installation/Setup
Classifier: Topic :: System :: Systems Administration
Classifier: Topic :: Utilities
Classifier: Natural Language :: English
Classifier: Intended Audience :: Science/Research
Classifier: Intended Audience :: System Administrators
Classifier: Environment :: Console
Requires-Dist: click (>=3.3)
Requires-Dist: GitPython (>=0.3)
Requires-Dist: PyYaml (>=3.10)
